data/licenses_nonobsolete_only.json
src/error.py
src/parse.py
src/scrap.py
src/test.py
src/tmp.py
src/type.py
licenses_spdx-0.1.0.dist-info/LICENSE
licenses_spdx-0.1.0.dist-info/WHEEL
licenses_spdx-0.1.0.dist-info/METADATA
licenses_spdx-0.1.0.dist-info/RECORD
